wellington/cli.py
wellington/installables/base.py
wellington/installables/command.py
wellington/installables/distro.py
wellington/installables/link.py
wellington/installables/node.py
wellington/installables/python.py
wellington/installables/rust.py
wellington/installables/vcs.py
wellington/util/merge.py
wellington/util/python_path.py
wellington-0.2.1.dist-info/METADATA
wellington-0.2.1.dist-info/WHEEL
wellington-0.2.1.dist-info/entry_points.txt
wellington-0.2.1.dist-info/RECORD
