Metadata-Version: 2.1
Name: wellington
Version: 0.2.1
Summary: A tool to help bootstrap your dev environment.
License: MPL-2.0
Author: Andrew Halberstadt
Author-email: ahal@pm.me
Requires-Python: >=3.7,<4.0
Classifier: License :: OSI Approved
Classifier: Programming Language :: Python :: 3
Classifier: Programming Language :: Python :: 3.7
Classifier: Programming Language :: Python :: 3.8
Classifier: Programming Language :: Python :: 3.9
Classifier: Programming Language :: Python :: 3.10
Classifier: Programming Language :: Python :: 3.11
Requires-Dist: tomli (>=1.2.2,<2.0.0)
